{"Movie":{"MakingNationNameKR":"기타","MakingNationNameUS":"기타","MakingNationName":null,"MovieGenreCode":"60","PlayTime":82,"SoundTypeCode":"100","SoundTypeNameKR":"일반사운드","SoundTypeNameUS":"일반사운드","FourDTypeCode":"100","FourDTypeNameKR":"일반","FourDTypeNameUS":"일반","TranslationDivisionCode":"","TranslationDivisionNameKR":"","TranslationDivisionNameUS":"","HomepageURL":"","SynopsisKR":"<b> &lt;보스 베이비&gt;&lt;마이펫의 이중생활&gt; 제작진의<br>올여름 가장 신나는 쿨썸머 매직 어드벤처! </b><br>&nbsp;<br><br>세계 제일의 캐리비안 해적 선장은<br>소원을 이뤄주는 마법 다이아몬드를 찾아 항해한다.<br><br>그러던 중 보물의 행적을 알고 있다는<br>최강 뽀시래기 해적단을 만나 함께 보물섬으로 향한다.<br><br>바다를 건너, 정글을 지나<br>욕심쟁이 뱀파이어왕 군단의 공격 속에서<br>마법 다이아몬드의 신비로운 빛을 발견하게 되는데…<br><br><b> 과연 소원을 이뤄주는 절대 보물의 주인은 누가 될까?! </b>","SynopsisUS":"<b> &lt;보스 베이비&gt;&lt;마이펫의 이중생활&gt; 제작진의<br>올여름 가장 신나는 쿨썸머 매직 어드벤처! </b><br>&nbsp;<br><br>세계 제일의 캐리비안 해적 선장은<br>소원을 이뤄주는 마법 다이아몬드를 찾아 항해한다.<br><br>그러던 중 보물의 행적을 알고 있다는<br>최강 뽀시래기 해적단을 만나 함께 보물섬으로 향한다.<br><br>바다를 건너, 정글을 지나<br>욕심쟁이 뱀파이어왕 군단의 공격 속에서<br>마법 다이아몬드의 신비로운 빛을 발견하게 되는데…<br><br><b> 과연 소원을 이뤄주는 절대 보물의 주인은 누가 될까?! </b>","Synopsis":null,"TotalViewCount":0,"AgePrefer10":"","AgePrefer20":"","AgePrefer30":"","AgePrefer40":"","ManPrefer":"","WomanPrefer":"","KOFCustCnt":0,"AggrDt":"","MakingNationNameKR2":"","MakingNationNameKR3":"","MovieGenreNameKR2":"","MovieGenreNameKR3":"","RepresentationMovieCode":"15986","MoviePlayYN":"N","MoviePlayEndYN":0,"MovieNameKR":"캐리비안 해적과 마법 다이아몬드","MovieNameUS":"캐리비안 해적과 마법 다이아몬드","MovieName":null,"PosterURL":"http://caching.lottecinema.co.kr//Media/MovieFile/MovieImg/202008/15986_103_1.jpg","ViewGradeCode":100,"ViewGradeNameKR":"관람등급미정","ViewGradeNameUS":"관람등급미정","ViewGradeName":null,"BookingRate":0,"ReleaseDate":"2020-08-31 오전 12:00:00","DDay":null,"ExpectEvaluation":0,"ViewEvaluation":0,"Evaluation":0,"BookingYN":"N","ViewRate":0,"SpecialScreenDivisionCode":[""],"SoloOpenYN":null,"OpenORClosing":0,"BookingRank":"-","ViewSortSequence":null,"BookingSortSequence":null,"FilmCode":"200","FilmName":"2D","MovieFestivalID":0,"DirectorName":null,"ActorName":null,"MovieGenreNameKR":"애니메이션","MovieGenreNameUS":"애니메이션","MovieGenreName":null,"ProductionCompanyName":"","MovieDivisionCode":null,"MovieFestivalName":null,"MovieFestivalFilmCount":null,"MovieFestivalOpenDate":null,"MovieFestivalFinalDate":null,"MovieFestivalOpenMovieCode":null,"MovieFestivalOpenMovieName":null,"MovieFestivalFinalMovieCode":null,"MovieFestivalFinalMovieName":null,"ImagePath":null,"ImageALT":null,"LinkDivisionCode":null,"ParameterEventID":null,"ParameterRepMovieCode":null,"URL":null,"PopupTitle":null,"KOFMovieCd":null,"PlanedRelsYN":0,"PlanedRelsMnth":"2020-08","KeywordID":null,"KeywordNm":null,"MoreLookCD":null,"MoreLookUrl":null,"MoreLookImgUrl":null,"MoreLookImgAlt":null,"UpdateYn":null,"ArrayStandardCd":null,"UpdateDt":null,"LikeYN":"N","ViewCount":0,"LikeCount":9,"TargetMovieListCode":0,"ViewCountSortSequence":0},"Casting":{"Items":[{"RepresentationMovieCode":"15986","StaffName":"이완 맥그리거","StaffImage":"http://caching.lottecinema.co.kr//Media/MovieFile/PersonImg/1000/1_107_2.jpg","Role":"감독"}]},"Trailer":{"ItemCount":1,"Items":[{"ImageDivisionCode":"1","ImageDivisionName":"Image","ImageURL":"http://caching.lottecinema.co.kr//Media/MovieFile/MovieImg/202008/15986_201_1.jpg","ImageAlter":"캐리비안 해적과 마법 다이아몬드","MediaURL":"","SortSequence":1,"ImageTypeCd":"201","MediaTitle":""}]},"TrailerDisabled":{"ItemCount":0,"Items":[]},"LikeYN":null,"IsOK":"true","ResultMessage":"SUCCESS","ResultCode":null,"EventResultYn":null}