{"castInfo":[{"RepresentationMovieCode":"16056","PersonCode":"53050","PersonName":"크리스티안 페촐트","CastName":"감독","PersonImgPath":"http://caching.lottecinema.co.kr//Media/MovieFile/PersonImg/54000/53050_107_1.jpg","creator":null,"createDts":null,"modifier":null,"modifyDts":null},{"RepresentationMovieCode":"16056","PersonCode":"104577","PersonName":"프란츠 로고스키","CastName":"게오르그","PersonImgPath":"http://caching.lottecinema.co.kr//Media/MovieFile/PersonImg/105000/104577_107_2.jpg","creator":null,"createDts":null,"modifier":null,"modifyDts":null},{"RepresentationMovieCode":"16056","PersonCode":"93522","PersonName":"파울라 베어","CastName":"마리","PersonImgPath":"http://caching.lottecinema.co.kr//Media/MovieFile/PersonImg/94000/93522_107_3.jpg","creator":null,"createDts":null,"modifier":null,"modifyDts":null}],"IsOK":"true","ResultMessage":"SUCCESS","ResultCode":null,"EventResultYn":null}