{"castInfo":[{"RepresentationMovieCode":"16055","PersonCode":"72133","PersonName":"마르잔 사트라피","CastName":"감독","PersonImgPath":"http://caching.lottecinema.co.kr//Media/MovieFile/PersonImg/73000/72133_107_1.jpg","creator":null,"createDts":null,"modifier":null,"modifyDts":null},{"RepresentationMovieCode":"16055","PersonCode":"19308","PersonName":"로자먼드 파이크","CastName":"","PersonImgPath":"http://caching.lottecinema.co.kr//Media/MovieFile/PersonImg/20000/19308_107_1.jpg","creator":null,"createDts":null,"modifier":null,"modifyDts":null},{"RepresentationMovieCode":"16055","PersonCode":"74582","PersonName":"샘 라일리","CastName":"","PersonImgPath":"http://caching.lottecinema.co.kr//Media/MovieFile/PersonImg/75000/74582_107_3.jpg","creator":null,"createDts":null,"modifier":null,"modifyDts":null},{"RepresentationMovieCode":"16055","PersonCode":"99733","PersonName":"안야 테일러-조이","CastName":"","PersonImgPath":"http://caching.lottecinema.co.kr//Media/MovieFile/PersonImg/100000/99733_107_3.jpg","creator":null,"createDts":null,"modifier":null,"modifyDts":null}],"IsOK":"true","ResultMessage":"SUCCESS","ResultCode":null,"EventResultYn":null}